tpdistance/__init__.py
tpdistance/distance.py
tpdistance/shortest.py
tpdistance/tpdistance.py
tpdistance-0.1.dist-info/LICENSE
tpdistance-0.1.dist-info/METADATA
tpdistance-0.1.dist-info/WHEEL
tpdistance-0.1.dist-info/top_level.txt
tpdistance-0.1.dist-info/RECORD
