Metadata-Version: 2.1
Name: tpdistance
Version: 0.1
Summary: Package to compute TP distances between nodes in a network.
Home-page: https://github.com/attilavarga/tpdistance
Author: Filipi N. Silva and Sadamori Kojaku and Attila Varga
Author-email: filsilva@iu.edu
License: UNKNOWN
Platform: UNKNOWN
Classifier: Programming Language :: Python :: 3
Classifier: License :: OSI Approved :: MIT License
Classifier: Operating System :: OS Independent
Requires-Python: >=3.0
License-File: LICENSE
Requires-Dist: numpy
Requires-Dist: tqdm
Requires-Dist: pandas
Requires-Dist: python-igraph
Requires-Dist: cxrandomwalk
Requires-Dist: networkx
Requires-Dist: fastnode2vec
